[
  {
    "id": 1,
    "title": "Изучить JavaScript",
    "description": "Освоить основы языка и продвинутые концепции. Изучить **ES6+** возможности и асинхронное программирование.",
    "status": "todo"
  },
  {
    "id": 2,
    "title": "Создать прототип приложения",
    "description": "Разработать **минимальный** рабочий прототип канбан-доски с базовым функционалом перетаскивания задач.",
    "status": "todo"
  },
  {
    "id": 3,
    "title": "Написать документацию",
    "description": "Подготовить подробную документацию для пользователей с примерами использования и _руководством по установке_.",
    "status": "in-progress"
  },
  {
    "id": 4,
    "title": "Протестировать функционал",
    "description": "Провести _тестирование_ всех функций приложения, включая создание, редактирование, удаление и перетаскивание задач.",
    "status": "in-progress"
  },
  {
    "id": 5,
    "title": "Исправить баги",
    "description": "Устранить найденные ошибки в коде, особенно в функции `handleDragDrop()` и валидации форм.",
    "status": "in-progress"
  },
  {
    "id": 6,
    "title": "Подготовить презентацию",
    "description": "Создать презентацию для демонстрации проекта с скриншотами и примерами использования.",
    "status": "done"
  },
  {
    "id": 7,
    "title": "Запустить проект",
    "description": "**Завершить** разработку и запустить проект на хостинге. Настроить CI/CD пайплайн.",
    "status": "done"
  }
]